ipaymu/__init__.py
ipaymu/bank.py
ipaymu/cod.py
ipaymu/compat.py
ipaymu/cstore.py
ipaymu/helper.py
ipaymu/v2/__init__.py
ipaymu/v2/utils.py
ipaymu/va.py
ipaymu-0.1.0.dist-info/LICENSE
ipaymu-0.1.0.dist-info/WHEEL
ipaymu-0.1.0.dist-info/METADATA
ipaymu-0.1.0.dist-info/RECORD
