Metadata-Version: 2.1
Name: ipaymu
Version: 0.1.0
Summary: IPaymu Client For Python (UNOFFICIAL)
Home-page: https://github.com/aprilahijriyan/ipaymu-python
License: MIT
Keywords: ipaymu,payment gateway
Author: aprilahijriyan
Author-email: hijriyan23@gmail.com
Requires-Python: >=3.7,<4.0
Classifier: Development Status :: 4 - Beta
Classifier: Intended Audience :: Developers
Classifier: License :: OSI Approved :: MIT License
Classifier: Operating System :: OS Independent
Classifier: Programming Language :: Python
Classifier: Programming Language :: Python :: 3
Classifier: Programming Language :: Python :: 3.7
Classifier: Programming Language :: Python :: 3.8
Classifier: Programming Language :: Python :: 3.9
Classifier: Topic :: Utilities
Requires-Dist: requests (>=2.26.0,<3.0.0)
Project-URL: Repository, https://github.com/aprilahijriyan/ipaymu-python
